README.md
setup.py
src/kkssh/__init__.py
src/kkssh/main.py
src/kkssh.egg-info/PKG-INFO
src/kkssh.egg-info/SOURCES.txt
src/kkssh.egg-info/dependency_links.txt
src/kkssh.egg-info/entry_points.txt
src/kkssh.egg-info/requires.txt
src/kkssh.egg-info/top_level.txt