Metadata-Version: 2.1
Name: kkssh
Version: 0.11
Summary: ssh client
Home-page: https://github.com/Beim/kkssh
Author: xingkun
Author-email: xingkunliu@qq.com
Keywords: ssh client
